gamayun/__GamayunResult_pb2.py
gamayun/__GamayunResult_pb2_grpc.py
gamayun/__init__.py
gamayun/gamayun_utils.py
gamayun_utils-0.2.1.1.dist-info/LICENSE
gamayun_utils-0.2.1.1.dist-info/METADATA
gamayun_utils-0.2.1.1.dist-info/WHEEL
gamayun_utils-0.2.1.1.dist-info/top_level.txt
gamayun_utils-0.2.1.1.dist-info/RECORD
