Metadata-Version: 2.1
Name: gamayun-utils
Version: 0.2.1.1
Summary: Python utils for writing gamayun job scripts
Home-page: https://github.com/ivan-brko/GamayunPyUtils
Author: Ivan Brko
Author-email: ivan.brko@outlook.com
License: UNKNOWN
Platform: UNKNOWN
Classifier: Programming Language :: Python :: 3
Classifier: License :: OSI Approved :: MIT License
Classifier: Operating System :: OS Independent
Requires-Python: >=3.6
Requires-Dist: grpcio (==1.30.0)
Requires-Dist: protobuf (==3.13.0)
